fds/__init__.py
fds/sdk/__init__.py
fds/sdk/NorthfieldPortfolioOptimizer/__init__.py
fds/sdk/NorthfieldPortfolioOptimizer/api_client.py
fds/sdk/NorthfieldPortfolioOptimizer/configuration.py
fds/sdk/NorthfieldPortfolioOptimizer/exceptions.py
fds/sdk/NorthfieldPortfolioOptimizer/model_utils.py
fds/sdk/NorthfieldPortfolioOptimizer/rest.py
fds/sdk/NorthfieldPortfolioOptimizer/api/__init__.py
fds/sdk/NorthfieldPortfolioOptimizer/api/accounts_api.py
fds/sdk/NorthfieldPortfolioOptimizer/api/currencies_api.py
fds/sdk/NorthfieldPortfolioOptimizer/api/npo_optimizer_api.py
fds/sdk/NorthfieldPortfolioOptimizer/api/strategy_documents_api.py
fds/sdk/NorthfieldPortfolioOptimizer/apis/__init__.py
fds/sdk/NorthfieldPortfolioOptimizer/model/__init__.py
fds/sdk/NorthfieldPortfolioOptimizer/model/account_directories.py
fds/sdk/NorthfieldPortfolioOptimizer/model/account_directories_root.py
fds/sdk/NorthfieldPortfolioOptimizer/model/calculation_info.py
fds/sdk/NorthfieldPortfolioOptimizer/model/calculation_info_root.py
fds/sdk/NorthfieldPortfolioOptimizer/model/client_error_response.py
fds/sdk/NorthfieldPortfolioOptimizer/model/constraint_action.py
fds/sdk/NorthfieldPortfolioOptimizer/model/currency.py
fds/sdk/NorthfieldPortfolioOptimizer/model/currency_root.py
fds/sdk/NorthfieldPortfolioOptimizer/model/document_directories.py
fds/sdk/NorthfieldPortfolioOptimizer/model/document_directories_root.py
fds/sdk/NorthfieldPortfolioOptimizer/model/error.py
fds/sdk/NorthfieldPortfolioOptimizer/model/error_source.py
fds/sdk/NorthfieldPortfolioOptimizer/model/npo_optimization_parameters.py
fds/sdk/NorthfieldPortfolioOptimizer/model/npo_optimization_parameters_root.py
fds/sdk/NorthfieldPortfolioOptimizer/model/npo_optimizer_strategy.py
fds/sdk/NorthfieldPortfolioOptimizer/model/npo_optimizer_strategy_overrides.py
fds/sdk/NorthfieldPortfolioOptimizer/model/object_root.py
fds/sdk/NorthfieldPortfolioOptimizer/model/optimal_portfolio.py
fds/sdk/NorthfieldPortfolioOptimizer/model/optimization.py
fds.sdk.NorthfieldPortfolioOptimizer-0.21.14.dist-info/LICENSE
fds.sdk.NorthfieldPortfolioOptimizer-0.21.14.dist-info/METADATA
fds.sdk.NorthfieldPortfolioOptimizer-0.21.14.dist-info/WHEEL
fds.sdk.NorthfieldPortfolioOptimizer-0.21.14.dist-info/top_level.txt
fds.sdk.NorthfieldPortfolioOptimizer-0.21.14.dist-info/RECORD
